LICENSE
MANIFEST.in
README.md
setup.py
libpythonpro/__init__.py
libpythonpro/github_api.py
libpythonpro/tests/__init__.py
libpythonpro/tests/test_exemplo.py
libpythonpro/tests/spam/__init__.py
libpythonpro/tests/spam/enviador_de_email.py
libpythonpro/tests/test_spam/__init__.py
libpythonpro/tests/test_spam/test_enviador_de_email.py
libpythonpro_rafa.egg-info/PKG-INFO
libpythonpro_rafa.egg-info/SOURCES.txt
libpythonpro_rafa.egg-info/dependency_links.txt
libpythonpro_rafa.egg-info/not-zip-safe
libpythonpro_rafa.egg-info/requires.txt
libpythonpro_rafa.egg-info/top_level.txt